MANIFEST.in
README.rst
setup.py
bin/obot
bin/obotctl
bin/obotd
files/obotd.service
obot/__init__.py
obot/adm.py
obot/cmd.py
obot/irc.py
obot/log.py
obot/rss.py
obot/tbl.py
obot/tdo.py
obot/udp.py
obot.egg-info/PKG-INFO
obot.egg-info/SOURCES.txt
obot.egg-info/dependency_links.txt
obot.egg-info/top_level.txt
olib/__init__.py
olib/bus.py
olib/clk.py
olib/dbs.py
olib/edt.py
olib/err.py
olib/evt.py
olib/fnd.py
olib/hdl.py
olib/itr.py
olib/ldr.py
olib/nms.py
olib/obj.py
olib/opt.py
olib/prs.py
olib/tbl.py
olib/thr.py
olib/tms.py
olib/trc.py
olib/trm.py
olib/url.py
olib/utl.py
olib/zzz.py
test/test_cfg.py
test/test_cmd.py
test/test_json.py
test/test_obj.py
test/test_thr.py